nvidia/nvimgcodec/include/nvcv_adapter.hpp
nvidia/nvimgcodec/include/nvimgcodec_version.h
nvidia/nvimgcodec/extensions/libnvpnm_ext.so.0.6.1
nvidia/nvimgcodec/include/nvimgcodec.h
nvidia_nvimgcodec_cu12-0.6.1.37.dist-info/LICENSE.txt
nvidia/nvimgcodec/__init__.py
nvidia/nvimgcodec/extensions/libnvbmp_ext.so.0.6.1
nvidia_nvimgcodec_cu12-0.6.1.37.dist-info/WHEEL
nvidia_nvimgcodec_cu12-0.6.1.37.dist-info/METADATA
nvidia_nvimgcodec_cu12-0.6.1.37.dist-info/top_level.txt
nvidia/__init__.py
nvidia/nvimgcodec/extensions/libjpeg_turbo_ext.so.0.6.1
nvidia/nvimgcodec/extensions/libtiff_ext.so.0.6.1
nvidia/nvimgcodec/nvimgcodec_impl.cpython-38-x86_64-linux-gnu.so
nvidia/nvimgcodec/extensions/libopencv_ext.so.0.6.1
nvidia/nvimgcodec/nvimgcodec_impl.cpython-311-x86_64-linux-gnu.so
nvidia/nvimgcodec/nvimgcodec_impl.cpython-313t-x86_64-linux-gnu.so
nvidia/nvimgcodec/libnvimgcodec.so.0
nvidia/nvimgcodec/nvimgcodec_impl.cpython-313-x86_64-linux-gnu.so
nvidia/nvimgcodec/nvimgcodec_impl.cpython-39-x86_64-linux-gnu.so
nvidia/nvimgcodec/nvimgcodec_impl.cpython-312-x86_64-linux-gnu.so
nvidia/nvimgcodec/extensions/libnvjpeg2k_ext.so.0.6.1
nvidia/nvimgcodec/extensions/libnvtiff_ext.so.0.6.1
nvidia/nvimgcodec/nvimgcodec_impl.cpython-310-x86_64-linux-gnu.so
nvidia/nvimgcodec/extensions/libnvjpeg_ext.so.0.6.1
nvidia_nvimgcodec_cu12-0.6.1.37.dist-info/RECORD
